cim_11/__init__.py
cim_11/cim-11.sqlite3
cim_11/stopwords.py
cim_11_certic-0.6.3.dist-info/LICENSE.txt
cim_11_certic-0.6.3.dist-info/METADATA
cim_11_certic-0.6.3.dist-info/WHEEL
cim_11_certic-0.6.3.dist-info/RECORD
