Metadata-Version: 2.1
Name: cim-11-CERTIC
Version: 0.6.3
Summary: Classification Internationale des Maladies Onzième Révision en français. Données OMS.
License: LICENSE.txt
Author: Mickaël Desfrênes
Author-email: mickael.desfrenes@unicaen.fr
Requires-Python: >=3.9
Classifier: License :: Other/Proprietary License
Classifier: Programming Language :: Python :: 3
Classifier: Programming Language :: Python :: 3.9
Classifier: Programming Language :: Python :: 3.10
Classifier: Programming Language :: Python :: 3.11
Classifier: Programming Language :: Python :: 3.12
